[
  {
    "main": "便利",
    "kana": "べんり",
    "romaji": "benri",
    "meaning": "convenient; handy; useful"
  },
  {
    "main": "大丈夫",
    "kana": "だいじょうぶ",
    "romaji": "daijoubu",
    "meaning": "OK; alright"
  },
  {
    "main": "大好き",
    "kana": "だいすき",
    "romaji": "daisuki",
    "meaning": "love; like; like very much"
  },
  {
    "main": "元気",
    "kana": "げんき",
    "romaji": "genki",
    "meaning": "lively; energetic; healthy"
  },
  {
    "main": "下手",
    "kana": "へた",
    "romaji": "heta",
    "meaning": "unskillful; poor; awkward"
  },
  {
    "main": "暇",
    "kana": "ひま",
    "romaji": "hima",
    "meaning": "free time"
  },
  {
    "main": "本当",
    "kana": "ほんとう",
    "romaji": "hontou",
    "meaning": "truth; reality; fact"
  },
  {
    "main": "色々",
    "kana": "いろいろ",
    "romaji": "iroiro",
    "meaning": "various"
  },
  {
    "main": "嫌",
    "kana": "いや",
    "romaji": "iya",
    "meaning": "unpleasant"
  },
  {
    "main": "丈夫",
    "kana": "じょうぶ",
    "romaji": "joubu",
    "meaning": "strong, durable"
  },
  {
    "main": "上手",
    "kana": "じょうず",
    "romaji": "jouzu",
    "meaning": "skillful; skilled; good (at)"
  },
  {
    "main": "結構",
    "kana": "けっこう",
    "romaji": "kekkou",
    "meaning": "splendid, enough"
  },
  {
    "main": "嫌い",
    "kana": "きらい",
    "romaji": "kirai",
    "meaning": "hate"
  },
  {
    "main": "綺麗",
    "kana": "きれい",
    "romaji": "kirei",
    "meaning": "pretty; lovely; beautiful"
  },
  {
    "main": "真っ直ぐ",
    "kana": "まっすぐ",
    "romaji": "massugu",
    "meaning": "straight ahead,direct"
  },
  {
    "main": "賑やか",
    "kana": "にぎやか",
    "romaji": "nigiyaka",
    "meaning": "bustling, busy"
  },
  {
    "main": "立派",
    "kana": "りっぱ",
    "romaji": "rippa",
    "meaning": "splendid"
  },
  {
    "main": "静か",
    "kana": "しずか",
    "romaji": "shizuka",
    "meaning": "quiet"
  },
  {
    "main": "好き",
    "kana": "すき",
    "romaji": "suki",
    "meaning": "like"
  },
  {
    "main": "多分",
    "kana": "たぶん",
    "romaji": "tabun",
    "meaning": "perhaps; probably"
  },
  {
    "main": "大変",
    "kana": "たいへん",
    "romaji": "taihen",
    "meaning": "very; greatly; difficult"
  },
  {
    "main": "大切",
    "kana": "たいせつ",
    "romaji": "taisetsu",
    "meaning": "important; beloved"
  },
  {
    "main": "沢山",
    "kana": "たくさん",
    "romaji": "takusan",
    "meaning": "many"
  },
  {
    "main": "有名",
    "kana": "ゆうめい",
    "romaji": "yuumei",
    "meaning": "famous"
  }
]